odoo/addons/delivery_mrw/README.rst
odoo/addons/delivery_mrw/__init__.py
odoo/addons/delivery_mrw/__manifest__.py
odoo/addons/delivery_mrw/data/delivery_mrw.xml
odoo/addons/delivery_mrw/i18n/delivery_mrw.pot
odoo/addons/delivery_mrw/i18n/es.po
odoo/addons/delivery_mrw/models/__init__.py
odoo/addons/delivery_mrw/models/delivery_carrier.py
odoo/addons/delivery_mrw/models/mrw_request.py
odoo/addons/delivery_mrw/models/stock_picking.py
odoo/addons/delivery_mrw/readme/CONFIGURE.rst
odoo/addons/delivery_mrw/readme/CONTRIBUTORS.rst
odoo/addons/delivery_mrw/readme/DESCRIPTION.rst
odoo/addons/delivery_mrw/readme/INSTALL.rst
odoo/addons/delivery_mrw/readme/ROADMAP.rst
odoo/addons/delivery_mrw/readme/USAGE.rst
odoo/addons/delivery_mrw/security/ir.model.access.csv
odoo/addons/delivery_mrw/static/description/icon.jpg
odoo/addons/delivery_mrw/static/description/icon.png
odoo/addons/delivery_mrw/static/description/index.html
odoo/addons/delivery_mrw/tests/__init__.py
odoo/addons/delivery_mrw/tests/test_delivery_mrw.py
odoo/addons/delivery_mrw/views/delivery_mrw_view.xml
odoo/addons/delivery_mrw/views/mrw_manifest_template.xml
odoo/addons/delivery_mrw/views/stock_picking_views.xml
odoo/addons/delivery_mrw/wizard/__init__.py
odoo/addons/delivery_mrw/wizard/mrw_manifest_wizard.py
odoo/addons/delivery_mrw/wizard/mrw_manifest_wizard_views.xml
odoo/addons/delivery_mrw/wizard/stock_immediate_transfer_views.xml
odoo/addons/delivery_mrw/wizard/stock_inmediate_transfer.py
odoo14_addon_delivery_mrw-14.0.1.1.4.dist-info/METADATA
odoo14_addon_delivery_mrw-14.0.1.1.4.dist-info/WHEEL
odoo14_addon_delivery_mrw-14.0.1.1.4.dist-info/top_level.txt
odoo14_addon_delivery_mrw-14.0.1.1.4.dist-info/RECORD
