Metadata-Version: 2.1
Name: odoo14-addon-delivery_mrw
Version: 14.0.1.1.4
Summary: Delivery Carrier implementation for MRW with SAGEC API
Home-page: https://github.com/OCA/l10n-spain
Author: Tecnativa, Odoo Community Association (OCA)
Author-email: support@odoo-community.org
License: AGPL-3
Classifier: Programming Language :: Python
Classifier: Framework :: Odoo
Classifier: Framework :: Odoo :: 14.0
Classifier: License :: OSI Approved :: GNU Affero General Public License v3
Requires-Python: >=3.6
Requires-Dist: odoo14-addon-delivery-package-number
Requires-Dist: odoo14-addon-delivery-state
Requires-Dist: odoo <14.1dev,>=14.0a
Requires-Dist: zeep
